README.md
setup.py
publicip/__init__.py
publicip.egg-info/PKG-INFO
publicip.egg-info/SOURCES.txt
publicip.egg-info/dependency_links.txt
publicip.egg-info/top_level.txt